<?xml version="1.0"?>
<skeleton>
 <id>artikulate-basic</id>
 <title>Artikulate Basic Course</title>
 <description>Artikulate Basic Course</description>
 <units>
  <unit>
   <id>{dd60f04a-eb37-44b7-9787-67aaf7d3578d}</id>
   <title>On the Street</title>
   <phrases>
    <phrase>
     <id>{3a4c1926-60d7-44c6-80d1-03165a641c75}</id>
     <text>Good day.</text>
     <type>sentence</type>
    </phrase>
    <phrase>
     <id>{56b0d0a2-8505-4a9e-89f7-a933824fac89}</id>
     <text>How are you?</text>
     <type>sentence</type>
    </phrase>
    <phrase>
     <id>{b65eced5-4d94-4c05-b738-244215da0b50}</id>
     <text></text>
     <type>word</type>
    </phrase>
   </phrases>
  </unit>
  <unit>
   <id>{6ab7d60e-b885-4833-97ff-27cb1ca2f543}</id>
   <title>Numbers</title>
   <phrases>
    <phrase>
     <id>{24e8ef0c-9234-4da5-a6fe-dbd5104f57d5}</id>
     <text>0</text>
     <type>word</type>
    </phrase>
    <phrase>
     <id>{ae91a229-b4a9-4264-9a26-75a55aa5d302}</id>
     <text>1</text>
     <type>word</type>
    </phrase>
    <phrase>
     <id>{8d7b65c2-e8f2-4153-86cc-9ed3293959d5}</id>
     <text>2</text>
     <type>word</type>
    </phrase>
    <phrase>
     <id>{b682e2bd-b16d-4eaf-9935-5eabaa97f1a1}</id>
     <text>3</text>
     <type>word</type>
    </phrase>
    <phrase>
     <id>{9718cb32-b05d-4f99-9f3a-e5e3973cfe2a}</id>
     <text>4</text>
     <type>word</type>
    </phrase>
    <phrase>
     <id>{b5e7f4e3-c265-427f-acb0-f9d1922d994b}</id>
     <text>5</text>
     <type>word</type>
    </phrase>
    <phrase>
     <id>{eafc05e9-0bb4-4c54-ae0c-990d2610b68b}</id>
     <text>6</text>
     <type>word</type>
    </phrase>
    <phrase>
     <id>{d24872ac-7751-41c4-b1c4-cf2a54bd95f5}</id>
     <text>7</text>
     <type>word</type>
    </phrase>
    <phrase>
     <id>{8178c10f-1204-4cc3-9023-69935eea0c1e}</id>
     <text>8</text>
     <type>word</type>
    </phrase>
    <phrase>
     <id>{01320417-9ccf-4bd7-8c66-659e68e2449a}</id>
     <text>9</text>
     <type>word</type>
    </phrase>
    <phrase>
     <id>{83a9943b-1d34-45a0-a446-b6388784b2de}</id>
     <text>10</text>
     <type>word</type>
    </phrase>
    <phrase>
     <id>{ebd67728-48e8-4dee-846b-a8d55f9173b4}</id>
     <text>11</text>
     <type>word</type>
    </phrase>
    <phrase>
     <id>{c1c55dc8-cfac-43df-bf61-f15d9d65cd17}</id>
     <text>12</text>
     <type>word</type>
    </phrase>
    <phrase>
     <id>{eccc866d-4600-4284-82b4-96fb1120fc7f}</id>
     <text>13</text>
     <type>word</type>
    </phrase>
    <phrase>
     <id>{b88e772d-5311-45f5-8628-259df44fafbe}</id>
     <text>14</text>
     <type>word</type>
    </phrase>
    <phrase>
     <id>{992b0dad-e3d3-428c-99fe-920e6646186d}</id>
     <text>15</text>
     <type>word</type>
    </phrase>
    <phrase>
     <id>{efd24631-c719-44e9-a5d5-bccfe4a32c10}</id>
     <text>16</text>
     <type>word</type>
    </phrase>
    <phrase>
     <id>{9b410c81-c696-4bbd-9dc1-76d30c981dc5}</id>
     <text>17</text>
     <type>word</type>
    </phrase>
    <phrase>
     <id>{a8119748-2dd9-4833-9bc7-956f3229b2be}</id>
     <text>18</text>
     <type>word</type>
    </phrase>
    <phrase>
     <id>{5e43eccb-80bc-46b9-807d-465540f26a9e}</id>
     <text>19</text>
     <type>word</type>
    </phrase>
    <phrase>
     <id>{f71d08ef-5349-4bdf-b934-f45711ad4f88}</id>
     <text>20</text>
     <type>word</type>
    </phrase>
    <phrase>
     <id>{213604b9-75ff-42bd-85bc-5db8db7c607a}</id>
     <text>21</text>
     <type>word</type>
    </phrase>
   </phrases>
  </unit>
  <unit>
   <id>{28d8f25f-ff78-4a79-9aff-1411de513d65}</id>
   <title>Alphabet</title>
   <phrases>
    <phrase>
     <id>{060b6311-c362-451d-a245-68887c63bd6f}</id>
     <text>A</text>
     <type>word</type>
    </phrase>
    <phrase>
     <id>{1181aba9-cc44-4715-97f1-f17b6764252b}</id>
     <text>B</text>
     <type>word</type>
    </phrase>
    <phrase>
     <id>{4a1c0d9b-126e-4ca9-8a01-55d192c60a6b}</id>
     <text>C</text>
     <type>word</type>
    </phrase>
    <phrase>
     <id>{09d629f5-b0d8-4b6a-8250-05010336a8e8}</id>
     <text>D</text>
     <type>word</type>
    </phrase>
    <phrase>
     <id>{6e23fb32-f5f2-48e6-bb9e-74e42d8baa16}</id>
     <text>E</text>
     <type>word</type>
    </phrase>
    <phrase>
     <id>{e38434d2-d10e-4f36-8c46-f91ff5ee3c37}</id>
     <text>F</text>
     <type>word</type>
    </phrase>
    <phrase>
     <id>{9b6b6670-e42c-411a-9ecf-e4b7393b83b4}</id>
     <text>G</text>
     <type>word</type>
    </phrase>
    <phrase>
     <id>{38e72852-abd0-4fb3-b4de-302f34dd9024}</id>
     <text>H</text>
     <type>word</type>
    </phrase>
    <phrase>
     <id>{fc484cb7-e3aa-4217-a837-c334712d5781}</id>
     <text>I</text>
     <type>word</type>
    </phrase>
    <phrase>
     <id>{6858fef3-9243-48f1-b02a-088b06c14946}</id>
     <text>J</text>
     <type>word</type>
    </phrase>
    <phrase>
     <id>{69099f11-b5ac-444c-b4c3-16d00303eb8e}</id>
     <text>K</text>
     <type>word</type>
    </phrase>
    <phrase>
     <id>{a4a0082c-1558-4090-9122-9491c1cc5c53}</id>
     <text>L</text>
     <type>word</type>
    </phrase>
    <phrase>
     <id>{fe194e00-9c71-4512-8b71-59fe924b7ae2}</id>
     <text>M</text>
     <type>word</type>
    </phrase>
    <phrase>
     <id>{48e2f464-731b-4532-ad13-1f72ce3a3c4a}</id>
     <text>N</text>
     <type>word</type>
    </phrase>
    <phrase>
     <id>{c93bbcdf-4e9d-410b-a7e6-c6fdfe10fedf}</id>
     <text>O</text>
     <type>word</type>
    </phrase>
    <phrase>
     <id>{855e5223-c7b2-4352-b010-4f7af903fdde}</id>
     <text>P</text>
     <type>word</type>
    </phrase>
    <phrase>
     <id>{90fb287a-3ddc-45d8-8e3c-267d9f9cbb9d}</id>
     <text>Q</text>
     <type>word</type>
    </phrase>
    <phrase>
     <id>{91417828-5a45-41a6-8569-c8b5b6031f80}</id>
     <text>R</text>
     <type>word</type>
    </phrase>
    <phrase>
     <id>{1883ac71-a239-4640-bc85-22b9127314cd}</id>
     <text>S</text>
     <type>word</type>
    </phrase>
    <phrase>
     <id>{f272f8b4-db77-45af-b041-7f612a3582d2}</id>
     <text>T</text>
     <type>word</type>
    </phrase>
    <phrase>
     <id>{78f84cb3-a595-4d3f-bc5a-b032ed3e50b1}</id>
     <text>U</text>
     <type>word</type>
    </phrase>
    <phrase>
     <id>{e3cd820a-0444-40ab-b1fd-8c441bf00a08}</id>
     <text>V</text>
     <type>word</type>
    </phrase>
    <phrase>
     <id>{bf6f88c0-87f9-4ad9-ab2c-d7644954451a}</id>
     <text>W</text>
     <type>word</type>
    </phrase>
    <phrase>
     <id>{deda3cb6-43ad-441b-b6f7-014b862d4154}</id>
     <text>X</text>
     <type>word</type>
    </phrase>
    <phrase>
     <id>{31480e8b-849c-448e-9c74-cd406189c9d1}</id>
     <text>Y</text>
     <type>word</type>
    </phrase>
    <phrase>
     <id>{dc13efc0-6f60-4a97-9c01-f35a18ef4cd8}</id>
     <text>Z</text>
     <type>word</type>
    </phrase>
   </phrases>
  </unit>
  <unit>
   <id>{b0b42671-d5d1-4d9c-9f2d-ef329e1dd6db}</id>
   <title>Tourism</title>
   <phrases>
    <phrase>
     <id>{93dfebcd-c4de-40b3-a243-96c9c5dcc39c}</id>
     <text>museum</text>
     <type>word</type>
    </phrase>
    <phrase>
     <id>{6320b3db-cefc-4abf-be0d-3cb1a790b53c}</id>
     <text>exit</text>
     <type>word</type>
    </phrase>
    <phrase>
     <id>{85b0ca16-4867-4d28-9c1f-604d4f5e8357}</id>
     <text>entry</text>
     <type>word</type>
    </phrase>
    <phrase>
     <id>{31533327-aa7e-45c6-875c-dea4ab78c945}</id>
     <text>restaurant</text>
     <type>word</type>
    </phrase>
    <phrase>
     <id>{d61b5ae6-8dcb-41bd-93f8-3a040504f968}</id>
     <text>map</text>
     <type>word</type>
    </phrase>
    <phrase>
     <id>{0a30c392-eaba-4d6f-83ab-ea503bc8e872}</id>
     <text>street</text>
     <type>word</type>
    </phrase>
    <phrase>
     <id>{a2c9b3b8-dbe6-4e32-b620-83dfad9facd6}</id>
     <text>corner</text>
     <type>word</type>
    </phrase>
    <phrase>
     <id>{50632f8c-002a-429e-9020-3b2189d2571b}</id>
     <text>airport</text>
     <type>word</type>
    </phrase>
    <phrase>
     <id>{d13fcba5-5bdc-49fe-8c62-aa2080c845f4}</id>
     <text>beach</text>
     <type>word</type>
    </phrase>
    <phrase>
     <id>{ef9b98e2-43c6-4196-83f6-576fc45f7240}</id>
     <text>supermarket</text>
     <type>word</type>
    </phrase>
    <phrase>
     <id>{6448bdd5-9905-46ec-8228-1949c954cb7f}</id>
     <text>shop</text>
     <type>word</type>
    </phrase>
    <phrase>
     <id>{869eacc5-48bc-4808-926d-aa02db9744a9}</id>
     <text>junction</text>
     <type>word</type>
    </phrase>
    <phrase>
     <id>{ec9594f5-0423-4b44-ac18-c9bffa9490b5}</id>
     <text>building</text>
     <type>word</type>
    </phrase>
    <phrase>
     <id>{9ecc4cd8-035d-4a89-a2dc-5c09f01f7faa}</id>
     <text>church</text>
     <type>word</type>
    </phrase>
    <phrase>
     <id>{5f064ba6-da80-419e-995e-0067a85f7e84}</id>
     <text>architecture</text>
     <type>word</type>
    </phrase>
    <phrase>
     <id>{97913d0b-b56d-435f-9b82-7b467819a58d}</id>
     <text>hotel</text>
     <type>word</type>
    </phrase>
    <phrase>
     <id>{57996f2a-f322-4852-af50-959993300262}</id>
     <text>reserve</text>
     <type>word</type>
    </phrase>
    <phrase>
     <id>{ca54934b-b6d6-4ba7-bff6-7236521bf207}</id>
     <text>ferry</text>
     <type>word</type>
    </phrase>
    <phrase>
     <id>{c3eb9c92-4ec6-48e7-a320-f42cf935ca83}</id>
     <text>zoo</text>
     <type>word</type>
    </phrase>
    <phrase>
     <id>{5ac09060-6657-4c62-8aa5-e80625fc3a4e}</id>
     <text>sculpture</text>
     <type>word</type>
    </phrase>
    <phrase>
     <id>{159a5191-4687-4cfc-af0c-fb04aa2fae39}</id>
     <text>exhibition</text>
     <type>word</type>
    </phrase>
    <phrase>
     <id>{e4d6bb09-3bd7-4775-9fb3-891db9a0c650}</id>
     <text>coach</text>
     <type>word</type>
    </phrase>
    <phrase>
     <id>{0a2305c4-8a0a-4698-b870-32e9d5c01726}</id>
     <text>underground</text>
     <type>word</type>
    </phrase>
    <phrase>
     <id>{644caa37-926f-4257-b423-34dcf183ae89}</id>
     <text>capital</text>
     <type>word</type>
    </phrase>
    <phrase>
     <id>{5d33ec6d-03e5-4d9d-9b04-0fe01a1754bb}</id>
     <text>brochure</text>
     <type>word</type>
    </phrase>
    <phrase>
     <id>{3410833e-aca1-407f-8c17-deab07da0cb8}</id>
     <text>cathedral</text>
     <type>word</type>
    </phrase>
    <phrase>
     <id>{688b1e7c-a542-41ea-8859-aaf25a156553}</id>
     <text>train station</text>
     <type>expression</type>
    </phrase>
    <phrase>
     <id>{2c28962d-cd9d-468b-b5b8-6d902b61fdba}</id>
     <text>souvenir shop</text>
     <type>expression</type>
    </phrase>
    <phrase>
     <id>{3ec0b2bf-99da-4e2d-9f22-473dcbd8ff62}</id>
     <text>tour guide</text>
     <type>expression</type>
    </phrase>
    <phrase>
     <id>{7f0823ae-fc6b-4a36-9ee3-00164f4168aa}</id>
     <text>hundred yards</text>
     <type>expression</type>
    </phrase>
    <phrase>
     <id>{d6400cb4-a19c-404c-904c-b08bd2f34083}</id>
     <text>National Gallery</text>
     <type>expression</type>
    </phrase>
    <phrase>
     <id>{724064ae-fb35-4b00-b077-b6e58e39b0fc}</id>
     <text>bed and breakfast (B&amp;B)</text>
     <type>expression</type>
    </phrase>
    <phrase>
     <id>{4ce008fc-8d8d-4cad-a109-bf885da73bb0}</id>
     <text>ticket office</text>
     <type>expression</type>
    </phrase>
    <phrase>
     <id>{87c58bf2-d6b5-4d7c-b186-d5afe5c48b9b}</id>
     <text>youth hostel</text>
     <type>expression</type>
    </phrase>
    <phrase>
     <id>{d8ccc087-a104-4325-bada-fddbe87adcb9}</id>
     <text> boat trip</text>
     <type>expression</type>
    </phrase>
    <phrase>
     <id>{17e2fb23-63b5-4d4e-a066-0037e7a5afb6}</id>
     <text>go sightseeing</text>
     <type>expression</type>
    </phrase>
    <phrase>
     <id>{509b9da0-4641-4bbe-945b-d99cf3ebb28c}</id>
     <text>art collection</text>
     <type>expression</type>
    </phrase>
    <phrase>
     <id>{1073c6d5-338d-4537-9a7b-a7589b16586f}</id>
     <text>old town</text>
     <type>expression</type>
    </phrase>
    <phrase>
     <id>{1b4bdae9-7f1b-478e-b387-4b2395b140b5}</id>
     <text>meeting point</text>
     <type>expression</type>
    </phrase>
    <phrase>
     <id>{da804619-a060-48ad-83c0-7989b3279ee3}</id>
     <text>opening times</text>
     <type>expression</type>
    </phrase>
    <phrase>
     <id>{6a16ea35-af10-48bd-b810-8e33c808a7e0}</id>
     <text>information booklet</text>
     <type>expression</type>
    </phrase>
    <phrase>
     <id>{4cee20bb-363b-44bb-901c-021d6108dcd8}</id>
     <text>take a photo</text>
     <type>expression</type>
    </phrase>
    <phrase>
     <id>{f52cf10c-09ae-4453-a0af-58dd5cc59c4e}</id>
     <text>tourist attraction</text>
     <type>expression</type>
    </phrase>
    <phrase>
     <id>{68dfe7bb-4f64-4995-b194-af299d59f162}</id>
     <text>go by bus</text>
     <type>expression</type>
    </phrase>
    <phrase>
     <id>{dd2695dc-7fb7-4a71-8bca-0c6a186f82ee}</id>
     <text>How far is the train station?</text>
     <type>sentence</type>
    </phrase>
    <phrase>
     <id>{eb292974-a18e-4e48-8237-bb480c7e5f0f}</id>
     <text>Turn right at the crossroads.</text>
     <type>sentence</type>
    </phrase>
    <phrase>
     <id>{a8efb03d-9e2e-4cbc-bdb1-ed7d54e8df5c}</id>
     <text>Go over the bridge.</text>
     <type>sentence</type>
    </phrase>
    <phrase>
     <id>{50102ee1-d95c-4c33-ad1d-ca57de2bbc66}</id>
     <text>Excuse me, could you tell me how to get to the post office?</text>
     <type>sentence</type>
    </phrase>
    <phrase>
     <id>{5962fd5a-9164-4777-8179-cda7d4b895b8}</id>
     <text>When does the next tour start?</text>
     <type>sentence</type>
    </phrase>
    <phrase>
     <id>{a983071c-0522-4055-aee7-f164f5f70334}</id>
     <text>Is the museum open on Saturdays?</text>
     <type>sentence</type>
    </phrase>
    <phrase>
     <id>{5c05b94b-6043-4ee1-97d2-f4fd854b2641}</id>
     <text>Can you take a photo of me?</text>
     <type>sentence</type>
    </phrase>
    <phrase>
     <id>{86d1143d-556d-4d75-925b-0e1f618cb297}</id>
     <text>The next bus stop is at the end of the street.</text>
     <type>sentence</type>
    </phrase>
    <phrase>
     <id>{f39cb506-2367-48b0-be53-0433c5eb19d1}</id>
     <text>We are going to meet at 6 o'clock in the town square.</text>
     <type>sentence</type>
    </phrase>
    <phrase>
     <id>{205bd4d4-3315-4ba0-beba-e76cb4d5d821}</id>
     <text>Let's go to  the city centre.</text>
     <type>sentence</type>
    </phrase>
    <phrase>
     <id>{ec13ea1d-352e-476b-b299-78a65a579c96}</id>
     <text>The zoo is next to the police station.</text>
     <type>sentence</type>
    </phrase>
    <phrase>
     <id>{91c058c1-7d53-4ec3-a822-756212ee254b}</id>
     <text>Can we get there by foot?</text>
     <type>sentence</type>
    </phrase>
    <phrase>
     <id>{e6d666ea-6693-404e-9e57-694fb8a3fdfc}</id>
     <text>What would you recommend to see in the first place?</text>
     <type>sentence</type>
    </phrase>
    <phrase>
     <id>{de0f3a0e-e42b-417b-b1ea-3c2c81eaedad}</id>
     <text>How much is the admission fee?</text>
     <type>sentence</type>
    </phrase>
    <phrase>
     <id>{4f2bd05d-7fca-4490-ba61-441c9b99456c}</id>
     <text>Do you have any free maps of the city?</text>
     <type>sentence</type>
    </phrase>
    <phrase>
     <id>{6becb819-6669-4f88-9fb8-b7ccba61bec7}</id>
     <text>Would you like to visit National Gallery?</text>
     <type>sentence</type>
    </phrase>
    <phrase>
     <id>{b466b72e-d7b9-4dbb-a30e-31e11879d0cf}</id>
     <text>Our final destination today will be a local distillery.</text>
     <type>sentence</type>
    </phrase>
    <phrase>
     <id>{4713c077-5ed2-4a49-95db-ee32fdfe2ce0}</id>
     <text>You must visit the old castle.</text>
     <type>sentence</type>
    </phrase>
    <phrase>
     <id>{76093973-630d-4a4b-835f-ea072ccfb1b9}</id>
     <text>Take the second exit at the roundabout. Continue straight ahead for about a mile. The museum will be on your right.</text>
     <type>paragraph</type>
    </phrase>
    <phrase>
     <id>{e20e8a6a-c9af-4f31-998e-a9d5e9561c0a}</id>
     <text>London is a capital of England. It is a diverse and exciting city with many attractions. The most visited tourist attractions are London Eye, the National Gallery and Tower of London. Also Buckingham Palace situated is in the city centre is a popular sight as it is the official residence of the British Queen. Every day in front of the palace Changing the Guard ceremony takes place. This is worth seeing while you are visiting London and it is usually witnessed by large crowds.</text>
     <type>paragraph</type>
    </phrase>
    <phrase>
     <id>{5de429b5-c6be-4f7f-93f9-fb70b57bc7b6}</id>
     <text>Welcome to Rome! Why don't you join us for a “hop on, hop off” sightseeing tour of the city... The buses leave every 15 minutes from the train station and stop at 10 different city attractions. You can get off the bus at any stop and enjoy your time in the local area for as long as you want. For more information come and ask tourist information office just next to the main train station entrance.</text>
     <type>paragraph</type>
    </phrase>
    <phrase>
     <id>{e970e556-5028-47d2-b130-774abe6fd3df}</id>
     <text>Last year we went for a weekend break to Edinburgh. We spent most of the trip sightseeing. We have visited the castle and the old town.</text>
     <type>paragraph</type>
    </phrase>
    <phrase>
     <id>{e7864b6c-dd16-4141-8752-6a42124ff5c6}</id>
     <text>The gallery is open Monday-Friday from 10 am until 5 pm.  Entrance fee is 10$ for adults and 5$ for children under 12 years of age. Photographing is strictly prohibited in the whole building and all  cameras must be left in the cloakroom.</text>
     <type>paragraph</type>
    </phrase>
   </phrases>
  </unit>
  <unit>
   <id>{53705f4a-2a84-476d-90bf-aea23d6df487}</id>
   <title>Family</title>
   <phrases>
    <phrase>
     <id>{a45209f9-2797-4b21-9e5f-cd2f65417515}</id>
     <text>mother</text>
     <type>word</type>
    </phrase>
    <phrase>
     <id>{f13aa413-12db-4ac4-970f-a049a02b7e30}</id>
     <text>father</text>
     <type>word</type>
    </phrase>
    <phrase>
     <id>{7cef4738-6d85-4685-a781-46a5a52d1af7}</id>
     <text>uncle</text>
     <type>word</type>
    </phrase>
    <phrase>
     <id>{bcfd006d-c3e8-49ef-bc08-0768c18c9cbe}</id>
     <text>aunt</text>
     <type>word</type>
    </phrase>
    <phrase>
     <id>{b81fd88c-bc00-4aea-a9cc-9489e566a00a}</id>
     <text>brother</text>
     <type>word</type>
    </phrase>
    <phrase>
     <id>{ca56ec04-0662-425d-ae9d-4f282a342fb5}</id>
     <text>sister</text>
     <type>word</type>
    </phrase>
    <phrase>
     <id>{65f2a6bd-5be6-4169-afb5-3581f8e06078}</id>
     <text>grandmother</text>
     <type>word</type>
    </phrase>
    <phrase>
     <id>{108a4ddf-8c9b-4632-9188-0a7cfda508a1}</id>
     <text>grandfather</text>
     <type>word</type>
    </phrase>
    <phrase>
     <id>{5c475011-d85f-47fa-9dd5-d83b230145f9}</id>
     <text>daughter</text>
     <type>word</type>
    </phrase>
    <phrase>
     <id>{c5ac8139-5acc-4c5e-b458-7cccdffa7105}</id>
     <text>son</text>
     <type>word</type>
    </phrase>
    <phrase>
     <id>{4a17e0b5-117f-4123-aa09-699debeb26d5}</id>
     <text>siblings</text>
     <type>word</type>
    </phrase>
    <phrase>
     <id>{3da7d5bb-73a4-4a15-92e7-b28f08fec585}</id>
     <text>grandson</text>
     <type>word</type>
    </phrase>
    <phrase>
     <id>{ff3ca9c7-09fc-42f8-bd91-807ef443acea}</id>
     <text>granddaughter</text>
     <type>word</type>
    </phrase>
    <phrase>
     <id>{56ff75ed-c079-467a-b702-d83e2aa940ec}</id>
     <text>wife</text>
     <type>word</type>
    </phrase>
    <phrase>
     <id>{e9d6f3c9-2adc-44da-b376-c47033d941dc}</id>
     <text>husband</text>
     <type>word</type>
    </phrase>
    <phrase>
     <id>{650e213c-3aa1-4c00-89d3-ae708208c742}</id>
     <text>niece</text>
     <type>word</type>
    </phrase>
    <phrase>
     <id>{6a867158-3c7f-48b7-9161-ea7317efe3f9}</id>
     <text>nephew</text>
     <type>word</type>
    </phrase>
    <phrase>
     <id>{89a5acb9-f4c3-44ec-abde-a2eb538f9eec}</id>
     <text>spouse</text>
     <type>word</type>
    </phrase>
    <phrase>
     <id>{8862489f-7972-497b-be5d-b4afead9b4cd}</id>
     <text>marriage</text>
     <type>word</type>
    </phrase>
    <phrase>
     <id>{226d188f-054e-48bc-8d66-342b14286a7a}</id>
     <text>couple</text>
     <type>word</type>
    </phrase>
    <phrase>
     <id>{65b33bbd-a5ba-45df-9b96-292e493220d5}</id>
     <text>cousin</text>
     <type>word</type>
    </phrase>
    <phrase>
     <id>{337596af-ef04-4d45-b73f-22bbf477447d}</id>
     <text>godson</text>
     <type>word</type>
    </phrase>
    <phrase>
     <id>{51a09dd3-ac20-4bd0-a571-ab8e6384b769}</id>
     <text>children</text>
     <type>word</type>
    </phrase>
    <phrase>
     <id>{5cab4a17-e261-460e-83b9-7219cbaac107}</id>
     <text>babe</text>
     <type>word</type>
    </phrase>
    <phrase>
     <id>{3bedbf55-a0b4-4b77-a037-ba8f5f3348d7}</id>
     <text>adopt</text>
     <type>word</type>
    </phrase>
    <phrase>
     <id>{b8751e3b-fa9e-4f9c-970c-2dbff5e212b9}</id>
     <text>relative</text>
     <type>word</type>
    </phrase>
    <phrase>
     <id>{f0ff8f87-6998-4186-82b0-a5195c3cd2e6}</id>
     <text>orphan</text>
     <type>word</type>
    </phrase>
    <phrase>
     <id>{89ae77b7-1653-4510-824e-12ad53d77951}</id>
     <text>disinherit</text>
     <type>word</type>
    </phrase>
    <phrase>
     <id>{13a560b9-0217-48bb-ace9-68606c7c260b}</id>
     <text>single</text>
     <type>word</type>
    </phrase>
    <phrase>
     <id>{0fb64cac-9f4b-48c6-84b9-5363acd8363b}</id>
     <text>family</text>
     <type>word</type>
    </phrase>
    <phrase>
     <id>{d9b61e3c-7ed8-4b23-b940-f95143b3a4b8}</id>
     <text>great grandfather</text>
     <type>expression</type>
    </phrase>
    <phrase>
     <id>{98afb7b3-0977-49d9-a445-6fe26ae08397}</id>
     <text>great grandmother</text>
     <type>expression</type>
    </phrase>
    <phrase>
     <id>{6fecb201-d3dc-4f22-81cf-de7fcdfde111}</id>
     <text>twin brothers</text>
     <type>expression</type>
    </phrase>
    <phrase>
     <id>{5642138b-8ebe-4a69-9dd9-3596ab757a56}</id>
     <text>twin sisters</text>
     <type>expression</type>
    </phrase>
    <phrase>
     <id>{f3e4fae7-4c2e-4228-858d-004b85489a37}</id>
     <text>step-father</text>
     <type>expression</type>
    </phrase>
    <phrase>
     <id>{bc83b5cc-90d3-4bb7-b4f6-b8ac53d4e504}</id>
     <text>step-mother</text>
     <type>expression</type>
    </phrase>
    <phrase>
     <id>{08bd9966-4282-4fdb-82d1-4d8f21bf29e4}</id>
     <text>ex-husband</text>
     <type>expression</type>
    </phrase>
    <phrase>
     <id>{df2d2387-2712-4e6d-9bb2-bcf7b5960be5}</id>
     <text>ex-wife</text>
     <type>expression</type>
    </phrase>
    <phrase>
     <id>{17e9b72d-f2c2-4e92-9b06-7dcecc76262d}</id>
     <text>bring up</text>
     <type>expression</type>
    </phrase>
    <phrase>
     <id>{fbf42837-2a51-4882-a5fb-2a40c6d444cc}</id>
     <text>foster child</text>
     <type>expression</type>
    </phrase>
    <phrase>
     <id>{6cbc3c63-65a5-4892-8e56-2a2e663b6d65}</id>
     <text>be divorced</text>
     <type>expression</type>
    </phrase>
    <phrase>
     <id>{bc4e9420-0424-4206-9d4f-7dfbd2878730}</id>
     <text>elder sister</text>
     <type>expression</type>
    </phrase>
    <phrase>
     <id>{0fa0a6cf-01e1-4ae1-9313-b85d4639b348}</id>
     <text>be married</text>
     <type>expression</type>
    </phrase>
    <phrase>
     <id>{a2746154-d49f-4e1f-aa5e-708d2b76f8f2}</id>
     <text>be engaged</text>
     <type>expression</type>
    </phrase>
    <phrase>
     <id>{fc9a8359-3689-481f-8708-c725f8309537}</id>
     <text>get on well</text>
     <type>expression</type>
    </phrase>
    <phrase>
     <id>{bb315977-2a75-4355-b1f2-eefbaa357a03}</id>
     <text>black sheep</text>
     <type>expression</type>
    </phrase>
    <phrase>
     <id>{a162d6d7-55d3-474c-bd77-e4062a7903a8}</id>
     <text>family gathering</text>
     <type>expression</type>
    </phrase>
    <phrase>
     <id>{b60de9ba-53fb-4df4-8893-31e67d022646}</id>
     <text>family name</text>
     <type>expression</type>
    </phrase>
    <phrase>
     <id>{71fb26a0-a8b4-4926-bbde-3e67d508c295}</id>
     <text>biological brother</text>
     <type>expression</type>
    </phrase>
    <phrase>
     <id>{368dabbd-e453-4104-ba9b-673048767000}</id>
     <text>be separated</text>
     <type>expression</type>
    </phrase>
    <phrase>
     <id>{28ea7f77-900f-4836-887c-7ebba9a00e0d}</id>
     <text>I have one younger brother and two sisters.</text>
     <type>sentence</type>
    </phrase>
    <phrase>
     <id>{8a74340e-5f78-48df-80ff-de6e94e416c0}</id>
     <text>My parents got divorced two years ago.</text>
     <type>sentence</type>
    </phrase>
    <phrase>
     <id>{2a3c6479-3d24-4d3f-a3ba-dfd367b9680e}</id>
     <text>My sister-in-law just got pregnant and she is expecting a babe. </text>
     <type>sentence</type>
    </phrase>
    <phrase>
     <id>{a0a49252-3009-4c0a-86f4-0bab74ec379f}</id>
     <text>My family lives in New York.</text>
     <type>sentence</type>
    </phrase>
    <phrase>
     <id>{eda7da2b-520e-44c6-b2ae-928b27af2db8}</id>
     <text>We have been married for 10 years and we have two children. </text>
     <type>sentence</type>
    </phrase>
    <phrase>
     <id>{70ed088d-d131-442d-b07e-531776d2c9d8}</id>
     <text>They are twins.</text>
     <type>sentence</type>
    </phrase>
    <phrase>
     <id>{ef982491-0319-41cb-93ff-c99a4adb6cf0}</id>
     <text>George is Robert's and Susan's father.</text>
     <type>sentence</type>
    </phrase>
    <phrase>
     <id>{b86467c0-f354-45f0-ada0-9f9d81c65d77}</id>
     <text>Are you married?</text>
     <type>sentence</type>
    </phrase>
    <phrase>
     <id>{b8f8243f-b323-4359-bbfd-7ad8ddc3ad00}</id>
     <text>Anne is the youngest child in our family.</text>
     <type>sentence</type>
    </phrase>
    <phrase>
     <id>{843e46b9-d6c2-4bc9-9f23-4af732aaff57}</id>
     <text>Carol and Michael are Robert's grandparents. </text>
     <type>sentence</type>
    </phrase>
    <phrase>
     <id>{a76df398-1e68-442e-8944-d4ca0c17aaaf}</id>
     <text>The modern nuclear family consists of dad the breadwinner, mum the housewife and several children.</text>
     <type>sentence</type>
    </phrase>
    <phrase>
     <id>{5af079ba-7415-42e6-ab66-805ca279808f}</id>
     <text>My mother died last year.</text>
     <type>sentence</type>
    </phrase>
    <phrase>
     <id>{c6ef1ec6-0c36-45bd-888a-3fc7a6d75157}</id>
     <text>My father is an engineer. </text>
     <type>sentence</type>
    </phrase>
    <phrase>
     <id>{383e2b89-9c86-4b6c-a7d1-2ab688625ef4}</id>
     <text>How big is your family?</text>
     <type>sentence</type>
    </phrase>
    <phrase>
     <id>{c8e812e6-d98e-4154-972a-acbd051e42cd}</id>
     <text>Do you have any siblings?</text>
     <type>sentence</type>
    </phrase>
    <phrase>
     <id>{801eeb35-50d2-4377-9bcf-0a2e9729ac0d}</id>
     <text>What is your family name?</text>
     <type>sentence</type>
    </phrase>
    <phrase>
     <id>{d715af37-b8c2-4f68-a8f0-fb1940717027}</id>
     <text>Are your parents separated or they still live together?</text>
     <type>sentence</type>
    </phrase>
    <phrase>
     <id>{9fe9aead-cfdd-4106-b6fe-3b9ff70607ca}</id>
     <text>Our family is very big. I have two brothers and three sisters. We also have twenty-one cousins: fourteen from my father's side of the family and  seven from my mother's side.</text>
     <type>paragraph</type>
    </phrase>
    <phrase>
     <id>{a45ad81d-c749-49e7-a752-25e8b358f093}</id>
     <text>Julia and Holy are twins and they look exactly the same. They have been brought up together and since they were kids their mother tried to dress them identically. There are many pictures in the family album where the girls are indistinguishable.</text>
     <type>paragraph</type>
    </phrase>
    <phrase>
     <id>{b4691fce-fcef-4d07-a854-b4378014e66a}</id>
     <text>My family is a rather a small one, with only three people, my father, my mother and me. My mother is a doctor and my father is a lawyer.</text>
     <type>paragraph</type>
    </phrase>
    <phrase>
     <id>{e6ad70f5-ff48-4ccb-a6ba-54ea6d8a3995}</id>
     <text>My parents got divorced a year ago. After the divorce my mother married a Canadian engineer and moved to Toronto.  My father stayed in Washington and I decided to live with him.</text>
     <type>paragraph</type>
    </phrase>
   </phrases>
  </unit>
  <unit>
   <id>{05f5f1d8-4c0a-4d61-b05a-b08b467ea94e}</id>
   <title>Sport</title>
   <phrases>
    <phrase>
     <id>{b0ad1fd6-e767-4653-8283-64cd3fe2b391}</id>
     <text>volleyball</text>
     <type>word</type>
    </phrase>
    <phrase>
     <id>{f5a6aac6-2af2-454a-af4e-f2f196a0e3ee}</id>
     <text>football</text>
     <type>word</type>
    </phrase>
    <phrase>
     <id>{b86133c9-610b-48a3-890c-191e1b9381b8}</id>
     <text>basketball</text>
     <type>word</type>
    </phrase>
    <phrase>
     <id>{49f57de6-c935-4e91-bff6-b54b4a3ba716}</id>
     <text>tennis</text>
     <type>word</type>
    </phrase>
    <phrase>
     <id>{4754b1fc-dc0f-43e9-8871-1e823a00ece4}</id>
     <text>karate</text>
     <type>word</type>
    </phrase>
    <phrase>
     <id>{3f03356b-d8a1-4415-a290-13cfb28fb58b}</id>
     <text>squash</text>
     <type>word</type>
    </phrase>
    <phrase>
     <id>{8e81d815-2754-4d25-a296-6d4e1d8e5b85}</id>
     <text>athletics</text>
     <type>word</type>
    </phrase>
    <phrase>
     <id>{bcb3b2af-f897-4223-b6e6-6bb6da0b72a9}</id>
     <text>swimming</text>
     <type>word</type>
    </phrase>
    <phrase>
     <id>{da3cca9e-4d87-4790-9f1c-abfaeef2ed99}</id>
     <text>hockey</text>
     <type>word</type>
    </phrase>
    <phrase>
     <id>{c6d05914-189d-4a83-ac58-6ba705420ab1}</id>
     <text>rugby</text>
     <type>word</type>
    </phrase>
    <phrase>
     <id>{75c9d101-0e32-40aa-9f89-b00277713458}</id>
     <text>skiing</text>
     <type>word</type>
    </phrase>
    <phrase>
     <id>{50c0411a-153b-4106-8c31-a84ebf09efe6}</id>
     <text>snowboarding</text>
     <type>word</type>
    </phrase>
    <phrase>
     <id>{77c3c5ae-7366-425a-8ad0-7d13d4963adf}</id>
     <text>fitness</text>
     <type>word</type>
    </phrase>
    <phrase>
     <id>{d5c92520-4251-4ba2-bba6-1ba49165b160}</id>
     <text>opponent</text>
     <type>word</type>
    </phrase>
    <phrase>
     <id>{eb51a170-01ac-4dbe-b2c8-7338995128c6}</id>
     <text>record</text>
     <type>word</type>
    </phrase>
    <phrase>
     <id>{a84f81ac-fd16-4bea-913c-a4f0ceb2908a}</id>
     <text>spectator</text>
     <type>word</type>
    </phrase>
    <phrase>
     <id>{80e12978-fefc-462d-ac97-80a3ee7b03dc}</id>
     <text>stadium</text>
     <type>word</type>
    </phrase>
    <phrase>
     <id>{0a0419bd-8408-4467-a36c-da04144664a7}</id>
     <text>score</text>
     <type>word</type>
    </phrase>
    <phrase>
     <id>{590c37a6-6674-4b70-90a9-aaa3841a660c}</id>
     <text>referee</text>
     <type>word</type>
    </phrase>
    <phrase>
     <id>{db779dea-1cb4-4693-a59c-f3cde5585ce7}</id>
     <text>pitch</text>
     <type>word</type>
    </phrase>
    <phrase>
     <id>{a41476b7-58f5-4504-9bd4-febeebf74040}</id>
     <text>coach</text>
     <type>word</type>
    </phrase>
    <phrase>
     <id>{b35a79e3-d6c6-40cd-a483-a836441874a4}</id>
     <text>athlete</text>
     <type>word</type>
    </phrase>
    <phrase>
     <id>{fd6a1c16-d676-4d30-a0d0-6e46550e888d}</id>
     <text>cycling</text>
     <type>word</type>
    </phrase>
    <phrase>
     <id>{7f60b129-c130-4b41-a584-ee16031ca4bf}</id>
     <text>boxing</text>
     <type>word</type>
    </phrase>
    <phrase>
     <id>{8e46076f-85b9-4782-bd2c-521ae488fc73}</id>
     <text>winter sports</text>
     <type>expression</type>
    </phrase>
    <phrase>
     <id>{5d041d55-48fe-469c-8ce7-b0821bc4d85a}</id>
     <text>Olympic Games</text>
     <type>expression</type>
    </phrase>
    <phrase>
     <id>{1239190b-8685-42d6-9b40-d8408783e559}</id>
     <text>sports fun</text>
     <type>expression</type>
    </phrase>
    <phrase>
     <id>{7be6d279-52aa-4173-a704-a5e6f9d0121f}</id>
     <text>play basketball</text>
     <type>expression</type>
    </phrase>
    <phrase>
     <id>{02aeb29b-933b-46b8-a04a-8d0e42a81c8d}</id>
     <text>tennis court</text>
     <type>expression</type>
    </phrase>
    <phrase>
     <id>{00f4b510-b27f-4dd3-8ddd-0d7ac8cbab16}</id>
     <text>football field</text>
     <type>expression</type>
    </phrase>
    <phrase>
     <id>{0e3679e7-e2ac-4dec-93fa-aa066b42f532}</id>
     <text>do jogging</text>
     <type>expression</type>
    </phrase>
    <phrase>
     <id>{b062ce57-98fa-4643-b335-33f3de03c2d1}</id>
     <text>ride a bike</text>
     <type>expression</type>
    </phrase>
    <phrase>
     <id>{80fef4e7-36fa-49d9-b01e-527e2ae44b8f}</id>
     <text> beach volleyball</text>
     <type>expression</type>
    </phrase>
    <phrase>
     <id>{7507bde1-5f41-4836-baea-db108477def1}</id>
     <text>Australian rules football</text>
     <type>expression</type>
    </phrase>
    <phrase>
     <id>{4b9b8449-ae55-4e47-8969-ae91983d1650}</id>
     <text>rugby match</text>
     <type>expression</type>
    </phrase>
    <phrase>
     <id>{506cfec9-6489-4bf4-8e9e-c655a49b1447}</id>
     <text>martial arts</text>
     <type>expression</type>
    </phrase>
    <phrase>
     <id>{4a6f39cc-aa7a-4047-94d0-c783d2e4358c}</id>
     <text>golf club</text>
     <type>expression</type>
    </phrase>
    <phrase>
     <id>{da93b103-6a30-4eb9-9070-9b96fd4e8cb0}</id>
     <text>horse racing event</text>
     <type>expression</type>
    </phrase>
    <phrase>
     <id>{b977ff67-7f24-43a5-9fb7-5a7aac60e286}</id>
     <text>competitive player</text>
     <type>expression</type>
    </phrase>
    <phrase>
     <id>{f7f97587-e141-4f32-9b50-20929ae4efec}</id>
     <text>national sport</text>
     <type>expression</type>
    </phrase>
    <phrase>
     <id>{d8133ce4-14a8-4d82-9241-af0718f05d4b}</id>
     <text>outdoor sport</text>
     <type>expression</type>
    </phrase>
    <phrase>
     <id>{6e3becd5-d8eb-46d9-b6fa-a9ce364a8b84}</id>
     <text>be fit</text>
     <type>expression</type>
    </phrase>
    <phrase>
     <id>{14a12df4-c6e6-4b80-a9ab-c042e7ce7d7f}</id>
     <text> aerobic exercise</text>
     <type>expression</type>
    </phrase>
    <phrase>
     <id>{d0b3978e-f7e3-4233-acb2-a1e7df110e84}</id>
     <text>healthy weight</text>
     <type>expression</type>
    </phrase>
    <phrase>
     <id>{0e5f8f40-5329-45e0-a191-63e745927919}</id>
     <text>team sport</text>
     <type>expression</type>
    </phrase>
    <phrase>
     <id>{4dce30f2-5298-477a-8468-e3b36ca6e354}</id>
     <text>I play tennis twice a week.</text>
     <type>sentence</type>
    </phrase>
    <phrase>
     <id>{82669d0f-31ff-4bf8-85db-ac1fe0be0a8c}</id>
     <text>What sports do you like? </text>
     <type>sentence</type>
    </phrase>
    <phrase>
     <id>{b1dd77b4-636e-4cf3-b5ea-3549e62fd829}</id>
     <text>Last night we went to a live basketball game.</text>
     <type>sentence</type>
    </phrase>
    <phrase>
     <id>{ad8c4d73-1f0a-4e1c-a601-957840786770}</id>
     <text> My grandfather was university boxing champion.</text>
     <type>sentence</type>
    </phrase>
    <phrase>
     <id>{bc4f163c-bd0f-421a-b1f4-ed50baced348}</id>
     <text>The Philadelphia Marathon is a popular athletic event.</text>
     <type>sentence</type>
    </phrase>
    <phrase>
     <id>{431526fb-25bc-434b-91a4-698b5e218d6b}</id>
     <text>Some people consider martial arts to be dangerous.</text>
     <type>sentence</type>
    </phrase>
    <phrase>
     <id>{4c5cef55-e0d6-4e98-8a38-5d941a66dc0f}</id>
     <text>Do you like watching football on TV?</text>
     <type>sentence</type>
    </phrase>
    <phrase>
     <id>{e9d451ab-9ccd-4152-8aaa-9376b4e54763}</id>
     <text>People often take up swimming to improve their fitness.</text>
     <type>sentence</type>
    </phrase>
    <phrase>
     <id>{c9c402ad-9f57-41c6-8842-9c4867a3e17a}</id>
     <text> Darts is a popular pub game.</text>
     <type>sentence</type>
    </phrase>
    <phrase>
     <id>{aaa6c5cc-0e72-4b15-abc4-c4d003bad926}</id>
     <text>Do you think this team will go to the finals?</text>
     <type>sentence</type>
    </phrase>
    <phrase>
     <id>{9897c4f3-a2e9-4a21-9f53-828585a5a914}</id>
     <text>London hosted 2012 Olympic Games.</text>
     <type>sentence</type>
    </phrase>
    <phrase>
     <id>{a7b4f177-3daa-48a5-8cbe-523e8c28a4d0}</id>
     <text> Chess is a sport that requires skills and intelligence.</text>
     <type>sentence</type>
    </phrase>
    <phrase>
     <id>{85e28aaa-bf38-49be-8fa9-6c6ecfb8f2cc}</id>
     <text>Basketball is a team sport that was invented in USA. </text>
     <type>sentence</type>
    </phrase>
    <phrase>
     <id>{e6ef007f-47ff-4fc4-b7a0-ea356bad5c59}</id>
     <text>Many families take their children and go ice skating in the evenings. </text>
     <type>sentence</type>
    </phrase>
    <phrase>
     <id>{3717bd9a-f51f-4b4f-8cef-d17d588ca2a7}</id>
     <text>Baseball is very popular in United States. </text>
     <type>sentence</type>
    </phrase>
    <phrase>
     <id>{f0adfacc-4566-4d29-8a77-6a8830f3538e}</id>
     <text>He did not pass the ball to the other player. </text>
     <type>sentence</type>
    </phrase>
    <phrase>
     <id>{fa039182-42e9-4ec2-ab58-387707689fdb}</id>
     <text>Today we are going to win.</text>
     <type>sentence</type>
    </phrase>
    <phrase>
     <id>{33073916-636d-48d7-9e82-9ddb7ab2e66a}</id>
     <text>This is the best football magazine. </text>
     <type>sentence</type>
    </phrase>
    <phrase>
     <id>{ada0b7be-ba0d-44a5-9b4b-e99456fd8bc7}</id>
     <text>Paula's father reads sports news everyday. </text>
     <type>sentence</type>
    </phrase>
    <phrase>
     <id>{b6369b8b-17df-478b-af81-b7f0edabd3cd}</id>
     <text>Let's celebrate the victory.</text>
     <type>sentence</type>
    </phrase>
    <phrase>
     <id>{93b45a67-97b7-47f3-b331-c01b7c57c153}</id>
     <text>My father goes jogging every day. He is very fit. </text>
     <type>paragraph</type>
    </phrase>
    <phrase>
     <id>{6df53553-810b-44ff-a722-a01728b5c6e7}</id>
     <text>I like to play sports. My favourite is badminton.</text>
     <type>paragraph</type>
    </phrase>
    <phrase>
     <id>{8867d861-0e56-4f93-8bb2-d58f76f5353c}</id>
     <text>Ian Thorpe is a famous Australian swimmer. He has won three gold medals in Sydney Summer Olympic Games.  </text>
     <type>paragraph</type>
    </phrase>
    <phrase>
     <id>{cdb98274-36af-406f-afcd-7f0ed3dddf2a}</id>
     <text>I have been thinking about exchanging our tennis tickets. Instead of going on Friday, we should go on Saturday. What do you think?</text>
     <type>paragraph</type>
    </phrase>
    <phrase>
     <id>{bca3de0e-252c-410a-bbad-88ecbb3f8fc1}</id>
     <text>In football game there are two teams playing. Each team consist of ten field players and a goalie. </text>
     <type>paragraph</type>
    </phrase>
   </phrases>
  </unit>
  <unit>
   <id>{b390b3da-121f-470b-a342-f51ee654dc9e}</id>
   <title>Countries and cultures</title>
   <phrases>
    <phrase>
     <id>{565a4bc9-884b-4104-a96e-fb5830792bb8}</id>
     <text>Greece</text>
     <type>word</type>
    </phrase>
    <phrase>
     <id>{7005dad7-79e4-49de-9636-c6a72689b5ea}</id>
     <text>Germany</text>
     <type>word</type>
    </phrase>
    <phrase>
     <id>{39ec664c-fb90-4e44-b3fe-5f4c0c5cf809}</id>
     <text>United States of America</text>
     <type>word</type>
    </phrase>
    <phrase>
     <id>{f3be58dc-59f0-46af-aaf8-d4fac7f39f35}</id>
     <text>Spain</text>
     <type>word</type>
    </phrase>
    <phrase>
     <id>{3da04216-0700-4fd4-b1bc-9f7b8fb03be8}</id>
     <text>France</text>
     <type>word</type>
    </phrase>
    <phrase>
     <id>{67f07b95-e524-46a8-9f13-794559c7d47d}</id>
     <text>Great Britain</text>
     <type>word</type>
    </phrase>
    <phrase>
     <id>{37abb84a-0dcb-4087-a453-13ad455ed302}</id>
     <text>Brazil</text>
     <type>word</type>
    </phrase>
    <phrase>
     <id>{f70b0692-8a4d-4642-8533-93213d7a9d86}</id>
     <text>Argentina</text>
     <type>word</type>
    </phrase>
    <phrase>
     <id>{a096001d-a154-4d16-8950-ed749aecc48d}</id>
     <text>Russia</text>
     <type>word</type>
    </phrase>
    <phrase>
     <id>{3180c47c-69fe-411a-a5a8-295febff5ab1}</id>
     <text>Canada</text>
     <type>word</type>
    </phrase>
    <phrase>
     <id>{b176862d-7684-4758-8f90-d5e273802d2a}</id>
     <text>Australia</text>
     <type>word</type>
    </phrase>
    <phrase>
     <id>{27849b42-f31c-4da0-aeb3-0169a575e07d}</id>
     <text>New Zealand </text>
     <type>word</type>
    </phrase>
    <phrase>
     <id>{5f15704c-5772-4b39-aac1-8abaab761c70}</id>
     <text>China</text>
     <type>word</type>
    </phrase>
    <phrase>
     <id>{b83341ef-7fe1-4566-b490-b5a69a54b1c5}</id>
     <text>India</text>
     <type>word</type>
    </phrase>
    <phrase>
     <id>{81e31083-47b5-4526-aa6c-ea975f813858}</id>
     <text>Japan</text>
     <type>word</type>
    </phrase>
    <phrase>
     <id>{98903ca5-3a97-4600-8861-a0d94c5fb15d}</id>
     <text>American</text>
     <type>word</type>
    </phrase>
    <phrase>
     <id>{20ec9757-7a35-40f7-a389-6bddb0786702}</id>
     <text>English</text>
     <type>word</type>
    </phrase>
    <phrase>
     <id>{ef7e1122-90d9-4655-986d-c0fa69414bc4}</id>
     <text>Canadian</text>
     <type>word</type>
    </phrase>
    <phrase>
     <id>{1b755772-da58-4694-b482-ed812a0b1b12}</id>
     <text>Spanish</text>
     <type>word</type>
    </phrase>
    <phrase>
     <id>{4c2f86d4-a09f-4175-ac70-ba23f826c0a6}</id>
     <text>Brazilian</text>
     <type>word</type>
    </phrase>
    <phrase>
     <id>{c2d8ac5c-3827-4be8-bfed-f687b816fb06}</id>
     <text>Argentinian</text>
     <type>word</type>
    </phrase>
    <phrase>
     <id>{5beab421-e04e-4d7b-b544-91d0f06f55f0}</id>
     <text>Japanese</text>
     <type>word</type>
    </phrase>
    <phrase>
     <id>{fdccc110-6d48-40d4-8e52-75bba6928881}</id>
     <text>Chinese</text>
     <type>word</type>
    </phrase>
    <phrase>
     <id>{638fdfe5-8b77-44fa-9402-978102fd638b}</id>
     <text>French</text>
     <type>word</type>
    </phrase>
    <phrase>
     <id>{5726ba83-871f-4007-8f0f-b4ba6a8f8a56}</id>
     <text>currency</text>
     <type>word</type>
    </phrase>
    <phrase>
     <id>{d3e44058-e136-45e5-9804-f1c86c9e6487}</id>
     <text>flag</text>
     <type>word</type>
    </phrase>
    <phrase>
     <id>{aa4d046a-55b2-4138-ac05-55f98efbb1bc}</id>
     <text>passport</text>
     <type>word</type>
    </phrase>
    <phrase>
     <id>{3527919b-8a7c-4880-a298-b98bc750fda2}</id>
     <text>speak a language</text>
     <type>expression</type>
    </phrase>
    <phrase>
     <id>{335bb3a1-712a-42d5-8e4a-bd02b24ca651}</id>
     <text>come from</text>
     <type>expression</type>
    </phrase>
    <phrase>
     <id>{1b61b73e-a5db-4a80-86de-c9dc99827a9b}</id>
     <text>traditional dress</text>
     <type>expression</type>
    </phrase>
    <phrase>
     <id>{eec7bd1a-4944-47fb-be0c-873fe4c40100}</id>
     <text>be fluent</text>
     <type>expression</type>
    </phrase>
    <phrase>
     <id>{b24165ba-6027-4e70-a0d3-2e46ad639c32}</id>
     <text>foreign country</text>
     <type>expression</type>
    </phrase>
    <phrase>
     <id>{efa99dc5-1498-4cbf-a2a8-3a5934a46f8a}</id>
     <text>regional outfit</text>
     <type>expression</type>
    </phrase>
    <phrase>
     <id>{c27bde10-87fd-493d-9e93-e00f143b987d}</id>
     <text>official language</text>
     <type>expression</type>
    </phrase>
    <phrase>
     <id>{bb1b66bd-4af2-4029-92df-ed70278d50bf}</id>
     <text>national dish</text>
     <type>expression</type>
    </phrase>
    <phrase>
     <id>{f27236b1-cd29-4008-93c5-7b08ef572cf8}</id>
     <text>capital city</text>
     <type>expression</type>
    </phrase>
    <phrase>
     <id>{492aac48-4c49-40bd-90a0-e3bf0d8a99c1}</id>
     <text>European Union</text>
     <type>expression</type>
    </phrase>
    <phrase>
     <id>{9a0983a0-491c-4de6-9580-1664868f6b18}</id>
     <text>go abroad</text>
     <type>expression</type>
    </phrase>
    <phrase>
     <id>{a7c7eb74-d770-485e-b06e-890525ec927c}</id>
     <text>travel overseas</text>
     <type>expression</type>
    </phrase>
    <phrase>
     <id>{a9be6a5e-7979-41dd-ab74-575082a52efe}</id>
     <text>mother tongue</text>
     <type>expression</type>
    </phrase>
    <phrase>
     <id>{af3a2074-66c1-4eb0-87b5-6234ce6d82cb}</id>
     <text>local dialect</text>
     <type>expression</type>
    </phrase>
    <phrase>
     <id>{d68b2825-e8a9-443b-9159-a4dfec6ff7e6}</id>
     <text> culture shock</text>
     <type>expression</type>
    </phrase>
    <phrase>
     <id>{fd8cbffa-3907-4d51-bcde-b7c20d4d1d77}</id>
     <text>cultural stereotype</text>
     <type>expression</type>
    </phrase>
    <phrase>
     <id>{71c5bf98-fe19-45cb-9f2d-28a27056a001}</id>
     <text>Where are you from?</text>
     <type>sentence</type>
    </phrase>
    <phrase>
     <id>{64be1424-598a-48fe-b0ee-7e075cdd8ff2}</id>
     <text>What is you nationality?</text>
     <type>sentence</type>
    </phrase>
    <phrase>
     <id>{53345892-f6f1-4c9f-ad05-45ec2290ca85}</id>
     <text>In Brazil people speak portuguese.</text>
     <type>sentence</type>
    </phrase>
    <phrase>
     <id>{6d6335a1-d7a1-453d-9815-e3bc926e5872}</id>
     <text> I am French. </text>
     <type>sentence</type>
    </phrase>
    <phrase>
     <id>{fc0a450f-bcbc-4ea7-a127-d815d2646c60}</id>
     <text>Polish and Check are Slavic languages.</text>
     <type>sentence</type>
    </phrase>
    <phrase>
     <id>{32a35a54-6b25-47bc-8ea7-7a2e05c39626}</id>
     <text> I live in Australia.</text>
     <type>sentence</type>
    </phrase>
    <phrase>
     <id>{8ab66404-44a6-446e-96eb-0cb7745d7ac7}</id>
     <text> I can speak Spanish, German and a bit of Italian.</text>
     <type>sentence</type>
    </phrase>
    <phrase>
     <id>{7240079e-64ea-403a-9ec6-13e059b6d97b}</id>
     <text>Haggis is a Scottish national dish.</text>
     <type>sentence</type>
    </phrase>
    <phrase>
     <id>{5ba2ee29-0342-46f7-a082-37d4452624fd}</id>
     <text>There are three colours on German flag: red, black and yellow.</text>
     <type>sentence</type>
    </phrase>
    <phrase>
     <id>{4916c445-b916-4afa-be27-f068247727d7}</id>
     <text>Warsaw is Poland's capital city. </text>
     <type>sentence</type>
    </phrase>
    <phrase>
     <id>{e4aa21fd-f647-45c5-98be-ffddba6111f4}</id>
     <text> What is a traditional Indian dish?</text>
     <type>sentence</type>
    </phrase>
    <phrase>
     <id>{b3fe2864-42a5-4bc2-8349-d3baa7dfaa1c}</id>
     <text>I was born in a small village in Salvador. </text>
     <type>sentence</type>
    </phrase>
    <phrase>
     <id>{758cb73e-7410-4708-9854-48f554248611}</id>
     <text>Italian dialect from south is very different from any other dialects spoken in the country.</text>
     <type>sentence</type>
    </phrase>
    <phrase>
     <id>{47d08943-2a92-45da-be63-f500d4b595b5}</id>
     <text>Los Angeles has a large amount of ethnic and cultural diversity.</text>
     <type>sentence</type>
    </phrase>
    <phrase>
     <id>{caebae74-e96a-4ced-9994-65d5e8c953a8}</id>
     <text> Eating turkey on Christmas Day in Australia is a tradition.</text>
     <type>sentence</type>
    </phrase>
    <phrase>
     <id>{f7e0fe37-846a-4190-b132-e5fba0461900}</id>
     <text>Russia is the largest country in the world.</text>
     <type>sentence</type>
    </phrase>
    <phrase>
     <id>{2a7ce4b0-8af9-429a-80b8-91f8fc341f92}</id>
     <text>Greece borders with Albania, Republic of Macedonia, Bulgaria and Turkey. </text>
     <type>sentence</type>
    </phrase>
    <phrase>
     <id>{3d1444b2-ac16-4756-98ff-c4e5aea14234}</id>
     <text> Switzerland has four official languages. They speak Italian, French, German and  Romansh. </text>
     <type>paragraph</type>
    </phrase>
    <phrase>
     <id>{58326819-3659-4317-b4ae-3b5ca03122e8}</id>
     <text>I have double nationality. I am a French citizen and I also have a British passport. </text>
     <type>paragraph</type>
    </phrase>
    <phrase>
     <id>{3d4fb2ea-67ba-431f-9b28-209869c96d91}</id>
     <text>Egypt is a country in north Africa. Its capital is Cairo and it has a population of over 90 million people.</text>
     <type>paragraph</type>
    </phrase>
    <phrase>
     <id>{32794fd5-6247-4d13-a3eb-5c42d265d628}</id>
     <text>I come from Spain and I was born in Barcelona. When I was four years old my family emigrated to USA and we stayed there until now. I can speak both Spanish and English. </text>
     <type>paragraph</type>
    </phrase>
   </phrases>
  </unit>
 </units>
</skeleton>
